[
{"region": "Arica y Parinacota", "hombres": 112581, "mujeres": 113487},
{"region": "Tarapacá", "hombres": 167793, "mujeres": 162765},
{"region": "Antofagasta", "hombres": 315014, "mujeres": 292520},
{"region": "Atacama", "hombres": 144420, "mujeres": 141748},
{"region": "Coquimbo", "hombres": 368774, "mujeres": 388812},
{"region": "Valparaíso", "hombres": 880215, "mujeres": 935687},
{"region": "Metropolitana", "hombres": 3462267, "mujeres": 3650541},
{"region": "O´Higgins", "hombres":453710, "mujeres": 460845},
{"region": " Maule", "hombres":511624, "mujeres": 533326 },
{"region": "Ñuble", "hombres":232587, "mujeres": 248022},
{"region": "Biobío", "hombres":750730, "mujeres":806075},
{"region": "La Araucanía", "hombres":465131, "mujeres": 492093},
{"region": "Los Ríos", "hombres":188847, "mujeres": 195990},
{"region": "Los Lagos", "hombres":409400, "mujeres": 419308},
{"region": "Aysén", "hombres":53647, "mujeres": 49511},
{"region": "Magallanes", "hombres":85249, "mujeres": 81284},


]